<?xml version="1.0" encoding="iso-8859-1"?>
<listing-data>
    <property>
        <external-id><![CDATA[92007101443]]></external-id>
        <location>
            <streetname><![CDATA[Cha Am Grand Condtel]]></streetname>
            <streetnumber><![CDATA[]]></streetnumber>
            <post-code><![CDATA[0]]></post-code>
            <area-code><![CDATA[76120]]></area-code>
            <district-code><![CDATA[7612]]></district-code>
            <region-code><![CDATA[76]]></region-code>
            <longitude><![CDATA[99.9711]]></longitude>
            <latitude><![CDATA[12.7649]]></latitude>
            <property-name><![CDATA[Cha Am Grand Condtel]]></property-name>
            <property-type-group><![CDATA[]]></property-type-group>
        </location>
        <details>
            <title><![CDATA[Beach Front Condominium Unit for Sale]]></title>
            <description><![CDATA[The unit located on the 28th floor of the building with panoramic sea views, comes fully furnished with good quality modern furnishing and is ready to move straight in having been newly renovated to a high quality with a large kitchen fully equipped.
<BR>
<BR>The unit comes with 2 en suite bedrooms. All bedrooms has fitted wardrobe. A large open plan living, dinning and kitchen provides a spacious indoor living area. 
<BR>
<BR>The project offers excellent communal facilities including snooker, pool, saunas, large swimming pool, putting area, restaurant and bar. 
<BR>
<BR>Located in the northern sector of Hua Hin 20 minutes from the centre. 
<BR>
<BR>Price negotiable for quick sale!]]></description>
            <features><![CDATA[BAL,AIRC,CARP]]></features>
            <amenities><![CDATA[SWI]]></amenities>
            <price-details>
                <price><![CDATA[8400000]]></price>
                <price-unit><![CDATA[]]></price-unit>
                <price-description><![CDATA[]]></price-description>
                <price-type><![CDATA[BAH]]></price-type>
                <currency-code/>
            </price-details>
            <rooms>
                <num-bedrooms><![CDATA[2]]></num-bedrooms>
                <extra-rooms><![CDATA[0]]></extra-rooms>
                <num-bathrooms><![CDATA[2]]></num-bathrooms>
            </rooms>
            <furnishing><![CDATA[]]></furnishing>
            <size-details>
                <floor-area><![CDATA[0]]></floor-area>
                <floor-size-x><![CDATA[]]></floor-size-x>
                <floor-size-y><![CDATA[]]></floor-size-y>
                <land-area><![CDATA[0]]></land-area>
                <land-size-x><![CDATA[]]></land-size-x>
                <land-size-y><![CDATA[]]></land-size-y>
            </size-details>
            <parking-spaces><![CDATA[]]></parking-spaces>
            <numberoffloors><![CDATA[34]]></numberoffloors>
            <floor-level><![CDATA[28]]></floor-level>
            <facing><![CDATA[EAST]]></facing>
        </details>
        <listing-type><![CDATA[SALE]]></listing-type>
        <agent-id><![CDATA[]]></agent-id>
        <custom-name><![CDATA[]]></custom-name>
        <custom-phone><![CDATA[]]></custom-phone>
        <custom-mobile><![CDATA[]]></custom-mobile>
        <custom-email><![CDATA[]]></custom-email>
        <tenure><![CDATA[]]></tenure>
        <sold><![CDATA[NO]]></sold>
        <photo>
            <picture-url>http://saga.softverk.co.th/saga.transport/ddproperty/479/1000000694/0.jpg</picture-url>
            <picture-caption></picture-caption>

        </photo>
    </property>
    <property>
        <external-id><![CDATA[92007101413]]></external-id>
        <location>
            <streetname><![CDATA[]]></streetname>
            <streetnumber><![CDATA[]]></streetnumber>
            <post-code><![CDATA[0]]></post-code>
            <area-code><![CDATA[77070]]></area-code>
            <district-code><![CDATA[]]></district-code>
            <region-code><![CDATA[77]]></region-code>
            <longitude><![CDATA[99.9476]]></longitude>
            <latitude><![CDATA[12.56]]></latitude>
            <property-name><![CDATA[]]></property-name>
            <property-type-group><![CDATA[]]></property-type-group>
        </location>
        <details>
            <title><![CDATA[Magnificent Views]]></title>
            <description><![CDATA[Spectacular views from this 5 star condo. Only a short drive to the centre of town. Close to Market Village, Bangkok hospital and all other tourist attractions.
<BR>
<BR>Living Area
<BR>The 8 x 8 spacious living area gives you the feeing of freedom, Large glass sliding doors open up to the large bacony, you can enjoy the magnificient views, perfect for entertaining friends.
<BR>
<BR>Kitchen
<BR>Has all the state of the art appliances you would expect in a condo of this quality lovely dining area.
<BR>Bedrooms
<BR>All Bedrooms have en-suites, walk in closets, the master bedroom has a jacuzzi, and leads out to balcony.
<BR>
<BR>Exterior.
<BR>Swimming pool , gardens and private parking.huge storage rooms.all apartments are fully furnished and fitted with top quality home theater devices, washing machines,dryers, and  dishwashers,  addition to 24 hours security guards, access to your apartment is equipped with a fingerprint access system.
<BR> All you need is your golf clubs everything else is waiting here for you.
<BR>]]></description>
            <features><![CDATA[BAL,AIRC,OPLAN,GARD,TERR,CARP]]></features>
            <amenities><![CDATA[JAC,SEC,SWI]]></amenities>
            <price-details>
                <price><![CDATA[15600000]]></price>
                <price-unit><![CDATA[]]></price-unit>
                <price-description><![CDATA[]]></price-description>
                <price-type><![CDATA[BAH]]></price-type>
                <currency-code/>
            </price-details>
            <rooms>
                <num-bedrooms><![CDATA[3]]></num-bedrooms>
                <extra-rooms><![CDATA[0]]></extra-rooms>
                <num-bathrooms><![CDATA[3]]></num-bathrooms>
            </rooms>
            <furnishing><![CDATA[]]></furnishing>
            <size-details>
                <floor-area><![CDATA[0]]></floor-area>
                <floor-size-x><![CDATA[]]></floor-size-x>
                <floor-size-y><![CDATA[]]></floor-size-y>
                <land-area><![CDATA[0]]></land-area>
                <land-size-x><![CDATA[]]></land-size-x>
                <land-size-y><![CDATA[]]></land-size-y>
            </size-details>
            <parking-spaces><![CDATA[]]></parking-spaces>
            <numberoffloors><![CDATA[1]]></numberoffloors>
            <floor-level><![CDATA[0]]></floor-level>
            <facing><![CDATA[]]></facing>
        </details>
        <listing-type><![CDATA[SALE]]></listing-type>
        <agent-id><![CDATA[]]></agent-id>
        <custom-name><![CDATA[]]></custom-name>
        <custom-phone><![CDATA[]]></custom-phone>
        <custom-mobile><![CDATA[]]></custom-mobile>
        <custom-email><![CDATA[]]></custom-email>
        <tenure><![CDATA[]]></tenure>
        <sold><![CDATA[NO]]></sold>
        <photo>
            <picture-url>http://saga.softverk.co.th/saga.transport/ddproperty/479/1000000781/0.jpg</picture-url>
            <picture-caption></picture-caption>

        </photo>
    </property>
    <property>
        <external-id><![CDATA[55000418]]></external-id>
        <location>
            <streetname><![CDATA[]]></streetname>
            <streetnumber><![CDATA[]]></streetnumber>
            <post-code><![CDATA[0]]></post-code>
            <area-code><![CDATA[]]></area-code>
            <district-code><![CDATA[7700]]></district-code>
            <region-code><![CDATA[77]]></region-code>
            <longitude><![CDATA[0]]></longitude>
            <latitude><![CDATA[0]]></latitude>
            <property-name><![CDATA[]]></property-name>
            <property-type-group><![CDATA[]]></property-type-group>
        </location>
        <details>
            <title><![CDATA[Property ready to develope]]></title>
            <description><![CDATA[.]]></description>
            <features><![CDATA[]]></features>
            <amenities><![CDATA[]]></amenities>
            <price-details>
                <price><![CDATA[8000000]]></price>
                <price-unit><![CDATA[]]></price-unit>
                <price-description><![CDATA[]]></price-description>
                <price-type><![CDATA[BAH]]></price-type>
                <currency-code/>
            </price-details>
            <rooms>
                <num-bedrooms><![CDATA[0]]></num-bedrooms>
                <extra-rooms><![CDATA[0]]></extra-rooms>
                <num-bathrooms><![CDATA[0]]></num-bathrooms>
            </rooms>
            <furnishing><![CDATA[]]></furnishing>
            <size-details>
                <floor-area><![CDATA[0]]></floor-area>
                <floor-size-x><![CDATA[0]]></floor-size-x>
                <floor-size-y><![CDATA[0]]></floor-size-y>
                <land-area><![CDATA[0]]></land-area>
                <land-size-x><![CDATA[]]></land-size-x>
                <land-size-y><![CDATA[]]></land-size-y>
            </size-details>
            <parking-spaces><![CDATA[0]]></parking-spaces>
            <numberoffloors><![CDATA[0]]></numberoffloors>
            <floor-level><![CDATA[0]]></floor-level>
            <facing><![CDATA[SOUTH]]></facing>
        </details>
        <listing-type><![CDATA[SALE]]></listing-type>
        <agent-id><![CDATA[]]></agent-id>
        <custom-name><![CDATA[]]></custom-name>
        <custom-phone><![CDATA[]]></custom-phone>
        <custom-mobile><![CDATA[]]></custom-mobile>
        <custom-email><![CDATA[]]></custom-email>
        <tenure><![CDATA[]]></tenure>
        <sold><![CDATA[NO]]></sold>
        <photo>
            <picture-url>http://saga.softverk.co.th/saga.transport/ddproperty/479/1000002276/1.jpg</picture-url>
            <picture-caption></picture-caption>

        </photo>
    </property>
    <property>
        <external-id><![CDATA[55000417]]></external-id>
        <location>
            <streetname><![CDATA[]]></streetname>
            <streetnumber><![CDATA[]]></streetnumber>
            <post-code><![CDATA[0]]></post-code>
            <area-code><![CDATA[]]></area-code>
            <district-code><![CDATA[7612]]></district-code>
            <region-code><![CDATA[78]]></region-code>
            <longitude><![CDATA[99.998]]></longitude>
            <latitude><![CDATA[0]]></latitude>
            <property-name><![CDATA[]]></property-name>
            <property-type-group><![CDATA[]]></property-type-group>
        </location>
        <details>
            <title><![CDATA[Property Beach front]]></title>
            <description><![CDATA[Beach Front Property.]]></description>
            <features><![CDATA[]]></features>
            <amenities><![CDATA[]]></amenities>
            <price-details>
                <price><![CDATA[750000000]]></price>
                <price-unit><![CDATA[]]></price-unit>
                <price-description><![CDATA[]]></price-description>
                <price-type><![CDATA[BAH]]></price-type>
                <currency-code/>
            </price-details>
            <rooms>
                <num-bedrooms><![CDATA[0]]></num-bedrooms>
                <extra-rooms><![CDATA[0]]></extra-rooms>
                <num-bathrooms><![CDATA[0]]></num-bathrooms>
            </rooms>
            <furnishing><![CDATA[]]></furnishing>
            <size-details>
                <floor-area><![CDATA[0]]></floor-area>
                <floor-size-x><![CDATA[0]]></floor-size-x>
                <floor-size-y><![CDATA[0]]></floor-size-y>
                <land-area><![CDATA[0]]></land-area>
                <land-size-x><![CDATA[]]></land-size-x>
                <land-size-y><![CDATA[]]></land-size-y>
            </size-details>
            <parking-spaces><![CDATA[0]]></parking-spaces>
            <numberoffloors><![CDATA[0]]></numberoffloors>
            <floor-level><![CDATA[0]]></floor-level>
            <facing><![CDATA[EAST]]></facing>
        </details>
        <listing-type><![CDATA[SALE]]></listing-type>
        <agent-id><![CDATA[]]></agent-id>
        <custom-name><![CDATA[]]></custom-name>
        <custom-phone><![CDATA[]]></custom-phone>
        <custom-mobile><![CDATA[]]></custom-mobile>
        <custom-email><![CDATA[]]></custom-email>
        <tenure><![CDATA[]]></tenure>
        <sold><![CDATA[NO]]></sold>
        <photo>
            <picture-url>http://saga.softverk.co.th/saga.transport/ddproperty/479/1000002275/1.jpg</picture-url>
            <picture-caption></picture-caption>

        </photo>
    </property>
    <property>
        <external-id><![CDATA[92007101435]]></external-id>
        <location>
            <streetname><![CDATA[]]></streetname>
            <streetnumber><![CDATA[]]></streetnumber>
            <post-code><![CDATA[0]]></post-code>
            <area-code><![CDATA[77110]]></area-code>
            <district-code><![CDATA[7711]]></district-code>
            <region-code><![CDATA[77]]></region-code>
            <longitude><![CDATA[99.9578]]></longitude>
            <latitude><![CDATA[12.5619]]></latitude>
            <property-name><![CDATA[]]></property-name>
            <property-type-group><![CDATA[]]></property-type-group>
        </location>
        <details>
            <title><![CDATA[INTERNATIONAL RESTAURANT FOR SALE.]]></title>
            <description><![CDATA[EXCELLENT CENTRAL LOCATION.
<BR>
<BR>Quality established restaurant. Located next to one of the busiest markets in town, this obviously attracts many customers.
<BR>
<BR>The restaurant offers Thai and International dishes specializing in French cuisine. There are two cooks and two waitresses, who have worked for the previous owners and are willing to stay on.
<BR>
<BR>Working hours are 11 am to 11 pm 7 days per week. 
<BR>Rent is 20,000 baht per month, electric and water is approx 10,000 baht per month.
<BR>
<BR>The restaurant seats 25 inside in air-con comfort, and 45 ( can be extended to 65  for groups or private parties) are located out on the terrace where you can watch sport on a large screen. 
<BR>There is private parking and ample parking in a large parking area.
<BR>
<BR>The owners have owned the restaurant for 8 months, but they have a young family and they are finding it hard to concentrate on their family and the restaurant.
<BR>
<BR>This is a golden opportunity to buy an established successful business and enjoy the quality lifestyle Hua Hin has to offer.
<BR>
<BR>To view the restaurant please contact Ian + 66 (0) 819211804.
<BR>]]></description>
            <features><![CDATA[AIRC,TERR,CARP]]></features>
            <amenities><![CDATA[]]></amenities>
            <price-details>
                <price><![CDATA[2800000]]></price>
                <price-unit><![CDATA[]]></price-unit>
                <price-description><![CDATA[]]></price-description>
                <price-type><![CDATA[BAH]]></price-type>
                <currency-code/>
            </price-details>
            <rooms>
                <num-bedrooms><![CDATA[0]]></num-bedrooms>
                <extra-rooms><![CDATA[0]]></extra-rooms>
                <num-bathrooms><![CDATA[0]]></num-bathrooms>
            </rooms>
            <furnishing><![CDATA[]]></furnishing>
            <size-details>
                <floor-area><![CDATA[0]]></floor-area>
                <floor-size-x><![CDATA[]]></floor-size-x>
                <floor-size-y><![CDATA[]]></floor-size-y>
                <land-area><![CDATA[0]]></land-area>
                <land-size-x><![CDATA[]]></land-size-x>
                <land-size-y><![CDATA[]]></land-size-y>
            </size-details>
            <parking-spaces><![CDATA[]]></parking-spaces>
            <numberoffloors><![CDATA[0]]></numberoffloors>
            <floor-level><![CDATA[0]]></floor-level>
            <facing><![CDATA[]]></facing>
        </details>
        <listing-type><![CDATA[SALE]]></listing-type>
        <agent-id><![CDATA[]]></agent-id>
        <custom-name><![CDATA[]]></custom-name>
        <custom-phone><![CDATA[]]></custom-phone>
        <custom-mobile><![CDATA[]]></custom-mobile>
        <custom-email><![CDATA[]]></custom-email>
        <tenure><![CDATA[]]></tenure>
        <sold><![CDATA[NO]]></sold>
        <photo>
            <picture-url>http://saga.softverk.co.th/saga.transport/ddproperty/479/1000000790/0.jpg</picture-url>
            <picture-caption></picture-caption>
        </photo>
        <photo>
            <picture-url>http://saga.softverk.co.th/saga.transport/ddproperty/479/1000000790/0.jpg</picture-url>
            <picture-caption></picture-caption>
        </photo>
    </property>
</listing-data>